database.py
main.py
iflow_mcp_mcp_oi_wiki-0.1.0.dist-info/METADATA
iflow_mcp_mcp_oi_wiki-0.1.0.dist-info/WHEEL
iflow_mcp_mcp_oi_wiki-0.1.0.dist-info/entry_points.txt
iflow_mcp_mcp_oi_wiki-0.1.0.dist-info/top_level.txt
iflow_mcp_mcp_oi_wiki-0.1.0.dist-info/RECORD
